{
    "_vcs_unit__2641598282": [
        "_vcs_unit__2641598282",
        "W13FI",
        "module",
        7
    ],
    "std": [
        "std",
        "reYIK",
        "module",
        0
    ],
    "ControlDecode16": [
        "ControlDecode16",
        "BVZ81",
        "module",
        0
    ],
    "cf_math_pkg": [
        "cf_math_pkg",
        "N2nk1",
        "module",
        0
    ],
    "defs_div_sqrt_mvp": [
        "defs_div_sqrt_mvp",
        "BpRsb",
        "module",
        0
    ],
    "fpnew_pkg": [
        "fpnew_pkg",
        "ZPW3s",
        "module",
        0
    ],
    "EXHazard": [
        "EXHazard",
        "Sd5LU",
        "module",
        8
    ],
    "preprocess_mvp": [
        "preprocess_mvp",
        "PaMmr",
        "module",
        0
    ],
    "rv32ic_warp": [
        "rv32ic_warp",
        "h5mYV",
        "module",
        0
    ],
    "mux_aluinput": [
        "mux_aluinput",
        "dD3Md",
        "module",
        0
    ],
    "lzc_0001": [
        "lzc_0001",
        "RJeFR",
        "module",
        0
    ],
    "norm_div_sqrt_mvp": [
        "norm_div_sqrt_mvp",
        "fEJa1",
        "module",
        0
    ],
    "div_sqrt_top_mvp": [
        "div_sqrt_top_mvp",
        "mHcKL",
        "module",
        0
    ],
    "OperandOrganizer": [
        "OperandOrganizer",
        "Ssncj",
        "module",
        5
    ],
    "lzc_0002": [
        "lzc_0002",
        "qprAD",
        "module",
        0
    ],
    "iteration_div_sqrt_mvp": [
        "iteration_div_sqrt_mvp",
        "V8sib",
        "module",
        0
    ],
    "lzc_0000": [
        "lzc_0000",
        "rB4Qp",
        "module",
        0
    ],
    "div_sqrt_mvp_wrapper": [
        "div_sqrt_mvp_wrapper",
        "k848q",
        "module",
        0
    ],
    "adder32": [
        "adder32",
        "FBCR7",
        "module",
        2
    ],
    "ex_out": [
        "ex_out",
        "R3pK1",
        "module",
        0
    ],
    "fpnew_opgroup_block_0003": [
        "fpnew_opgroup_block_0003",
        "G9zMF",
        "module",
        0
    ],
    "fpnew_opgroup_block_0000": [
        "fpnew_opgroup_block_0000",
        "CqMwP",
        "module",
        0
    ],
    "fpnew_opgroup_block_0002": [
        "fpnew_opgroup_block_0002",
        "JsDcx",
        "module",
        0
    ],
    "Ctrl": [
        "Ctrl",
        "f7BvP",
        "module",
        0
    ],
    "mul32_0000": [
        "mul32_0000",
        "Dm3Ix",
        "module",
        3
    ],
    "rv32m_warp": [
        "rv32m_warp",
        "RqqDK",
        "module",
        0
    ],
    "mul_16": [
        "mul_16",
        "IjL5w",
        "module",
        4
    ],
    "TbAll": [
        "TbAll",
        "BJtVG",
        "module",
        0
    ],
    "Csr": [
        "Csr",
        "WBsM0",
        "module",
        9
    ],
    "PipeStage2": [
        "PipeStage2",
        "za9ZI",
        "module",
        0
    ],
    "DecodeHazard": [
        "DecodeHazard",
        "WKmKr",
        "module",
        0
    ],
    "RegFile": [
        "RegFile",
        "vQSI9",
        "module",
        10
    ],
    "Dcache": [
        "Dcache",
        "upATB",
        "module",
        0
    ],
    "Mem": [
        "Mem",
        "J9IJd",
        "module",
        0
    ],
    "Wb": [
        "Wb",
        "kDnFs",
        "module",
        0
    ],
    "Decode": [
        "Decode",
        "jfqR3",
        "module",
        0
    ],
    "ImmGenMux16": [
        "ImmGenMux16",
        "SJVbS",
        "module",
        0
    ],
    "RFaddrMux16": [
        "RFaddrMux16",
        "zxqvJ",
        "module",
        6
    ],
    "...MASTER...": [
        "SIM",
        "amcQw",
        "module",
        0
    ]
}